bleu_api/__init__.py
bleu_api/client.py
bleu_api-1.0.2.dist-info/LICENSE
bleu_api-1.0.2.dist-info/METADATA
bleu_api-1.0.2.dist-info/WHEEL
bleu_api-1.0.2.dist-info/top_level.txt
bleu_api-1.0.2.dist-info/RECORD
