Metadata-Version: 2.1
Name: bleu-api
Version: 1.0.2
Summary: API for Bleu
Author-email: Jahanzaib Malik <jzmalik123@gmail.com>
Project-URL: Homepage, https://github.com/jzmalik123/bleu-api
Project-URL: Bug Tracker, https://github.com/jzmalik123/bleu-api/issues
Classifier: Programming Language :: Python :: 3
Classifier: License :: OSI Approved :: MIT License
Classifier: Operating System :: OS Independent
Requires-Python: >=3.7
License-File: LICENSE
